lightCV/infer/__init__.py
lightCV/infer/yolov5_openvino.py
lightCV/labels_tool/__init__.py
lightCV/labels_tool/auto_label.py
lightCV/labels_tool/py_tools.py
lightCV-0.0.1.dist-info/LICENSE.txt
lightCV-0.0.1.dist-info/METADATA
lightCV-0.0.1.dist-info/WHEEL
lightCV-0.0.1.dist-info/top_level.txt
lightCV-0.0.1.dist-info/RECORD
