Metadata-Version: 2.1
Name: lightCV
Version: 0.0.1
Summary: A small tool package
Author-email: Nxp <142091247@qq.com>
Project-URL: Homepage, https://github.com/1402091247/pytools
Classifier: Programming Language :: Python :: 3
Classifier: License :: OSI Approved :: MIT License
Classifier: Operating System :: OS Independent
Requires-Python: >=3.7
License-File: LICENSE.txt
